uas_messenger/__init__.py
uas_messenger/message.py
uas_messenger/publisher.py
uas_messenger/subscriber.py
uas_messenger-1.1.0.dist-info/licenses/LICENSE
uas_messenger-1.1.0.dist-info/METADATA
uas_messenger-1.1.0.dist-info/WHEEL
uas_messenger-1.1.0.dist-info/top_level.txt
uas_messenger-1.1.0.dist-info/RECORD
