Metadata-Version: 2.4
Name: uas-messenger
Version: 1.1.0
Summary: A ZeroMQ API for the PSU UAS Club
Author-email: The Pennsylvania State University Unmanned Aerial Systems Club <psuuasofficial@gmail.com>
License-Expression: GPL-3.0
Classifier: Development Status :: 4 - Beta
Classifier: Intended Audience :: Developers
Classifier: Programming Language :: Python :: 3
Classifier: Topic :: Scientific/Engineering
Classifier: Operating System :: OS Independent
Classifier: Natural Language :: English
License-File: LICENSE
Requires-Dist: pydantic>=2.12.2
Requires-Dist: pyzmq>=27.1.0
Dynamic: license-file
